awsegy/__init__.py
awsegy/main.py
awsegy-0.1.4.dist-info/METADATA
awsegy-0.1.4.dist-info/WHEEL
awsegy-0.1.4.dist-info/entry_points.txt
awsegy-0.1.4.dist-info/top_level.txt
awsegy-0.1.4.dist-info/RECORD
